brotli_asgi/__init__.py
brotli_asgi-1.5.0.dist-info/licenses/LICENSE.md
brotli_asgi-1.5.0.dist-info/METADATA
brotli_asgi-1.5.0.dist-info/WHEEL
brotli_asgi-1.5.0.dist-info/top_level.txt
brotli_asgi-1.5.0.dist-info/RECORD
